{
  "updated": "2026-06-23T10:00:09.135226+00:00",
  "symbol": "XAUUSD",
  "dry_run": true,
  "position": "FLAT",
  "surprise_buf_len": 785,
  "history": [
    {
      "timestamp": "2026-06-23T10:00:09.135226+00:00",
      "signal": 0.0,
      "effective_signal": 0.0,
      "lots": 0.0,
      "S_t": 0.0002119196578860283,
      "atr_pct": 0.0049016162899380225,
      "equity": 100000.0,
      "dir_prob": 0.48436158895492554,
      "vol_regime": 2,
      "action_taken": "hold"
    },
    {
      "timestamp": "2026-06-23T09:00:07.549403+00:00",
      "signal": 0.0,
      "effective_signal": 0.0,
      "lots": 0.0,
      "S_t": 0.0007360959425568581,
      "atr_pct": 0.0049581505827555866,
      "equity": 100000.0,
      "dir_prob": 0.48480579257011414,
      "vol_regime": 2,
      "action_taken": "hold"
    },
    {
      "timestamp": "2026-06-23T08:00:06.037301+00:00",
      "signal": 0.0,
      "effective_signal": 0.0,
      "lots": 0.0,
      "S_t": 6.725441198796034e-05,
      "atr_pct": 0.0049696317900916965,
      "equity": 100000.0,
      "dir_prob": 0.4834223687648773,
      "vol_regime": 2,
      "action_taken": "hold"
    },
    {
      "timestamp": "2026-06-23T07:00:04.473227+00:00",
      "signal": 0.0,
      "effective_signal": 0.0,
      "lots": 0.0,
      "S_t": 8.951278869062662e-05,
      "atr_pct": 0.004804781032964693,
      "equity": 100000.0,
      "dir_prob": 0.4825221002101898,
      "vol_regime": 2,
      "action_taken": "hold"
    },
    {
      "timestamp": "2026-06-23T06:00:02.825814+00:00",
      "signal": 0.0,
      "effective_signal": 0.0,
      "lots": 0.0,
      "S_t": 0.00032721212483011186,
      "atr_pct": 0.004853178286208029,
      "equity": 100000.0,
      "dir_prob": 0.48231813311576843,
      "vol_regime": 2,
      "action_taken": "hold"
    },
    {
      "timestamp": "2026-06-23T05:00:11.012951+00:00",
      "signal": 0.0,
      "effective_signal": 0.0,
      "lots": 0.0,
      "S_t": 0.0006400858401320875,
      "atr_pct": 0.004819098217234416,
      "equity": 100000.0,
      "dir_prob": 0.48236456513404846,
      "vol_regime": 2,
      "action_taken": "hold"
    },
    {
      "timestamp": "2026-06-23T04:00:09.210589+00:00",
      "signal": 0.0,
      "effective_signal": 0.0,
      "lots": 0.0,
      "S_t": 0.00027447863249108195,
      "atr_pct": 0.004559255138886152,
      "equity": 100000.0,
      "dir_prob": 0.4810832440853119,
      "vol_regime": 2,
      "action_taken": "hold"
    },
    {
      "timestamp": "2026-06-23T03:00:07.535089+00:00",
      "signal": 0.0,
      "effective_signal": 0.0,
      "lots": 0.0,
      "S_t": 9.966293873731047e-05,
      "atr_pct": 0.004555836149338912,
      "equity": 100000.0,
      "dir_prob": 0.4803463816642761,
      "vol_regime": 2,
      "action_taken": "hold"
    },
    {
      "timestamp": "2026-06-23T02:00:05.538184+00:00",
      "signal": 0.0,
      "effective_signal": 0.0,
      "lots": 0.0,
      "S_t": 0.00011821730004157871,
      "atr_pct": 0.004577713297091157,
      "equity": 100000.0,
      "dir_prob": 0.48003605008125305,
      "vol_regime": 2,
      "action_taken": "hold"
    },
    {
      "timestamp": "2026-06-23T01:00:10.532943+00:00",
      "signal": 0.0,
      "effective_signal": 0.0,
      "lots": 0.0,
      "S_t": 0.00026232650270685554,
      "atr_pct": 0.0040026007055586395,
      "equity": 100000.0,
      "dir_prob": 0.4802517890930176,
      "vol_regime": 2,
      "action_taken": "hold"
    },
    {
      "timestamp": "2026-06-23T00:00:08.526899+00:00",
      "signal": 0.0,
      "effective_signal": 0.0,
      "lots": 0.0,
      "S_t": 0.00038921862142160535,
      "atr_pct": 0.004015796290240498,
      "equity": 100000.0,
      "dir_prob": 0.4795041084289551,
      "vol_regime": 2,
      "action_taken": "hold"
    },
    {
      "timestamp": "2026-06-22T23:00:06.596308+00:00",
      "signal": 0.0,
      "effective_signal": 0.0,
      "lots": 0.0,
      "S_t": 0.00014745160297024995,
      "atr_pct": 0.004163044489735394,
      "equity": 100000.0,
      "dir_prob": 0.47905316948890686,
      "vol_regime": 2,
      "action_taken": "hold"
    },
    {
      "timestamp": "2026-06-22T22:00:06.920769+00:00",
      "signal": 0.0,
      "effective_signal": 0.0,
      "lots": 0.0,
      "S_t": 0.00020899031369481236,
      "atr_pct": 0.004317215814533987,
      "equity": 100000.0,
      "dir_prob": 0.47904080152511597,
      "vol_regime": 2,
      "action_taken": "hold"
    },
    {
      "timestamp": "2026-06-22T21:00:05.164653+00:00",
      "signal": 0.0,
      "effective_signal": 0.0,
      "lots": 0.0,
      "S_t": 0.00023339048493653536,
      "atr_pct": 0.0044792853928006604,
      "equity": 100000.0,
      "dir_prob": 0.4787995219230652,
      "vol_regime": 2,
      "action_taken": "hold"
    },
    {
      "timestamp": "2026-06-22T20:00:03.569114+00:00",
      "signal": 0.0,
      "effective_signal": 0.0,
      "lots": 0.0,
      "S_t": 9.118410525843501e-05,
      "atr_pct": 0.0044792853928006604,
      "equity": 100000.0,
      "dir_prob": 0.4783235490322113,
      "vol_regime": 2,
      "action_taken": "hold"
    },
    {
      "timestamp": "2026-06-22T19:00:11.286613+00:00",
      "signal": 0.0,
      "effective_signal": 0.0,
      "lots": 0.0,
      "S_t": 0.00046088529052212834,
      "atr_pct": 0.0044792853928006604,
      "equity": 100000.0,
      "dir_prob": 0.47838887572288513,
      "vol_regime": 2,
      "action_taken": "hold"
    },
    {
      "timestamp": "2026-06-22T18:00:09.577229+00:00",
      "signal": 0.0,
      "effective_signal": 0.0,
      "lots": 0.0,
      "S_t": 0.00011420501687098294,
      "atr_pct": 0.004642012595846681,
      "equity": 100000.0,
      "dir_prob": 0.4781489968299866,
      "vol_regime": 2,
      "action_taken": "hold"
    },
    {
      "timestamp": "2026-06-22T17:00:08.010712+00:00",
      "signal": 0.0,
      "effective_signal": 0.0,
      "lots": 0.0,
      "S_t": 0.00031987333204597235,
      "atr_pct": 0.004725323974934012,
      "equity": 100000.0,
      "dir_prob": 0.477817177772522,
      "vol_regime": 2,
      "action_taken": "hold"
    },
    {
      "timestamp": "2026-06-22T16:00:06.305364+00:00",
      "signal": 0.0,
      "effective_signal": 0.0,
      "lots": 0.0,
      "S_t": 0.00030726694967597723,
      "atr_pct": 0.004758278478346831,
      "equity": 100000.0,
      "dir_prob": 0.4780958294868469,
      "vol_regime": 2,
      "action_taken": "hold"
    },
    {
      "timestamp": "2026-06-22T15:00:04.499450+00:00",
      "signal": 0.0,
      "effective_signal": 0.0,
      "lots": 0.0,
      "S_t": 0.0003873943060170859,
      "atr_pct": 0.00452797069043852,
      "equity": 100000.0,
      "dir_prob": 0.47757837176322937,
      "vol_regime": 2,
      "action_taken": "hold"
    },
    {
      "timestamp": "2026-06-22T14:00:03.005383+00:00",
      "signal": 0.0,
      "effective_signal": 0.0,
      "lots": 0.0,
      "S_t": 0.0002914949436672032,
      "atr_pct": 0.004430689864340971,
      "equity": 100000.0,
      "dir_prob": 0.4773668348789215,
      "vol_regime": 2,
      "action_taken": "hold"
    },
    {
      "timestamp": "2026-06-22T13:00:11.368397+00:00",
      "signal": 0.0,
      "effective_signal": 0.0,
      "lots": 0.0,
      "S_t": 0.00017027977446559817,
      "atr_pct": 0.004358464399529146,
      "equity": 100000.0,
      "dir_prob": 0.47715693712234497,
      "vol_regime": 2,
      "action_taken": "hold"
    },
    {
      "timestamp": "2026-06-22T12:00:09.811950+00:00",
      "signal": 0.0,
      "effective_signal": 0.0,
      "lots": 0.0,
      "S_t": 0.00035485392436385155,
      "atr_pct": 0.004320385343515489,
      "equity": 100000.0,
      "dir_prob": 0.47719597816467285,
      "vol_regime": 2,
      "action_taken": "hold"
    },
    {
      "timestamp": "2026-06-22T11:00:08.102657+00:00",
      "signal": 0.0,
      "effective_signal": 0.0,
      "lots": 0.0,
      "S_t": 0.00015521288150921464,
      "atr_pct": 0.0044007624590936415,
      "equity": 100000.0,
      "dir_prob": 0.47683581709861755,
      "vol_regime": 2,
      "action_taken": "hold"
    },
    {
      "timestamp": "2026-06-22T10:00:06.526613+00:00",
      "signal": 0.0,
      "effective_signal": 0.0,
      "lots": 0.0,
      "S_t": 0.00017382230726070702,
      "atr_pct": 0.004542838472218249,
      "equity": 100000.0,
      "dir_prob": 0.47741732001304626,
      "vol_regime": 2,
      "action_taken": "hold"
    },
    {
      "timestamp": "2026-06-22T09:00:04.453449+00:00",
      "signal": 0.0,
      "effective_signal": 0.0,
      "lots": 0.0,
      "S_t": 0.000489775906316936,
      "atr_pct": 0.004644698286425601,
      "equity": 100000.0,
      "dir_prob": 0.4770848751068115,
      "vol_regime": 2,
      "action_taken": "hold"
    },
    {
      "timestamp": "2026-06-22T08:00:02.620109+00:00",
      "signal": 0.0,
      "effective_signal": 0.0,
      "lots": 0.0,
      "S_t": 0.00041306435014121234,
      "atr_pct": 0.004970549078462139,
      "equity": 100000.0,
      "dir_prob": 0.4789324998855591,
      "vol_regime": 2,
      "action_taken": "hold"
    },
    {
      "timestamp": "2026-06-22T07:00:10.185698+00:00",
      "signal": 0.0,
      "effective_signal": 0.0,
      "lots": 0.0,
      "S_t": 0.00017492787446826696,
      "atr_pct": 0.004970549078462139,
      "equity": 100000.0,
      "dir_prob": 0.47941023111343384,
      "vol_regime": 2,
      "action_taken": "hold"
    },
    {
      "timestamp": "2026-06-22T06:00:08.268673+00:00",
      "signal": 0.0,
      "effective_signal": 0.0,
      "lots": 0.0,
      "S_t": 0.00022512451687362045,
      "atr_pct": 0.005061665533194978,
      "equity": 100000.0,
      "dir_prob": 0.48064330220222473,
      "vol_regime": 2,
      "action_taken": "hold"
    },
    {
      "timestamp": "2026-06-22T05:00:26.707973+00:00",
      "signal": 0.0,
      "effective_signal": 0.0,
      "lots": 0.0,
      "S_t": 9.900203440338373e-05,
      "atr_pct": 0.005111354547309662,
      "equity": 100000.0,
      "dir_prob": 0.4820941090583801,
      "vol_regime": 2,
      "action_taken": "hold"
    },
    {
      "timestamp": "2026-06-22T04:00:11.241743+00:00",
      "signal": 0.0,
      "effective_signal": 0.0,
      "lots": 0.0,
      "S_t": 0.00020552634669002146,
      "atr_pct": 0.005305026557153591,
      "equity": 100000.0,
      "dir_prob": 0.48370039463043213,
      "vol_regime": 2,
      "action_taken": "hold"
    },
    {
      "timestamp": "2026-06-22T03:00:09.702092+00:00",
      "signal": 0.0,
      "effective_signal": 0.0,
      "lots": 0.0,
      "S_t": 0.000704087084159255,
      "atr_pct": 0.005336123663942564,
      "equity": 100000.0,
      "dir_prob": 0.4853946566581726,
      "vol_regime": 2,
      "action_taken": "hold"
    },
    {
      "timestamp": "2026-06-22T02:00:06.699053+00:00",
      "signal": 0.0,
      "effective_signal": 0.0,
      "lots": 0.0,
      "S_t": 0.002034400589764118,
      "atr_pct": 0.005433355339861003,
      "equity": 100000.0,
      "dir_prob": 0.4843830168247223,
      "vol_regime": 2,
      "action_taken": "hold"
    },
    {
      "timestamp": "2026-06-22T01:00:04.639678+00:00",
      "signal": 0.0,
      "effective_signal": 0.0,
      "lots": 0.0,
      "S_t": 0.0009197578765451908,
      "atr_pct": 0.004620556211776875,
      "equity": 100000.0,
      "dir_prob": 0.49007925391197205,
      "vol_regime": 2,
      "action_taken": "hold"
    },
    {
      "timestamp": "2026-06-22T00:05:00.812909+00:00",
      "signal": 0.0,
      "effective_signal": 0.0,
      "lots": 0.0,
      "S_t": 0.00020493562624324113,
      "atr_pct": 0.004620556211776875,
      "equity": 100000.0,
      "dir_prob": 0.48979687690734863,
      "vol_regime": 2,
      "action_taken": "hold"
    }
  ],
  "status": "running"
}